[
    {
        "id": "anastassi-xenos",
        "name": "Anastassi Xenos",
        "puzzles": 341,
        "plw": 1038,
        "uscf": 826,
        "group": "King 4",
        "pokemonId": 493,
        "pokemonName": "Arceus",
        "tier": "legendary",
        "delta": 2
    },
    {
        "id": "karitas-farrell",
        "name": "Karitas Farrell",
        "puzzles": 185,
        "plw": 370,
        "uscf": 0,
        "group": "Pawn 1",
        "pokemonId": 491,
        "pokemonName": "Darkrai",
        "tier": "legendary",
        "delta": 1
    },
    {
        "id": "ethan-metzer",
        "name": "Ethan Metzer",
        "puzzles": 121,
        "plw": 363,
        "uscf": 897,
        "group": "King 43",
        "pokemonId": 250,
        "pokemonName": "Ho-Oh",
        "tier": "legendary",
        "delta": 3
    },
    {
        "id": "drew-murphy",
        "name": "Drew Murphy",
        "puzzles": 94,
        "plw": 282,
        "uscf": 787,
        "group": "King 21",
        "pokemonId": 789,
        "pokemonName": "Cosmog",
        "tier": "legendary",
        "delta": 5
    },
    {
        "id": "jeremy-chow",
        "name": "Jeremy Chow",
        "puzzles": 83,
        "plw": 176,
        "uscf": 260,
        "group": "King 8",
        "pokemonId": 493,
        "pokemonName": "Arceus",
        "tier": "legendary",
        "delta": 1
    },
    {
        "id": "sloane-murphy",
        "name": "Sloane Murphy",
        "puzzles": 83,
        "plw": 249,
        "uscf": 1335,
        "group": "King 72",
        "pokemonId": 716,
        "pokemonName": "Xerneas",
        "tier": "legendary",
        "delta": 2
    },
    {
        "id": "abby-noy",
        "name": "Abby Noy",
        "puzzles": 63,
        "plw": 126,
        "uscf": 751,
        "group": "Queen 8",
        "pokemonId": 792,
        "pokemonName": "Lunala",
        "tier": "legendary",
        "delta": 4
    },
    {
        "id": "jaxson-vanderpoole",
        "name": "Jaxson Vanderpoole",
        "puzzles": 60,
        "plw": 190,
        "uscf": 605,
        "group": "King 16",
        "pokemonId": 645,
        "pokemonName": "Landorus",
        "tier": "legendary",
        "delta": 0
    },
    {
        "id": "benjamin-burke",
        "name": "Benjamin Burke",
        "puzzles": 60,
        "plw": 140,
        "uscf": 0,
        "group": "Queen 4",
        "pokemonId": 802,
        "pokemonName": "Marshadow",
        "tier": "legendary",
        "delta": 2
    },
    {
        "id": "rafael-boquin",
        "name": "Rafael Boquin",
        "puzzles": 59,
        "plw": 158,
        "uscf": 509,
        "group": "Queen 2",
        "pokemonId": 243,
        "pokemonName": "Raikou",
        "tier": "legendary",
        "delta": 0
    },
    {
        "id": "chloe-yip",
        "name": "Chloe Yip",
        "puzzles": 54,
        "plw": 182,
        "uscf": 850,
        "group": "King 12",
        "pokemonId": 892,
        "pokemonName": "Urshifu",
        "tier": "legendary",
        "delta": 1
    },
    {
        "id": "isha-varma",
        "name": "Isha Varma",
        "puzzles": 50,
        "plw": 150,
        "uscf": 1302,
        "group": "King 20",
        "pokemonId": 384,
        "pokemonName": "Rayquaza",
        "tier": "legendary",
        "delta": 0
    },
    {
        "id": "jayden-duke",
        "name": "Jayden Duke",
        "puzzles": 49,
        "plw": 268,
        "uscf": 453,
        "group": "Rook 5",
        "pokemonId": 144,
        "pokemonName": "Articuno",
        "tier": "legendary",
        "delta": 2
    },
    {
        "id": "parker-downing",
        "name": "PARKER DOWNING",
        "puzzles": 47,
        "plw": 104,
        "uscf": 150,
        "group": "King 33",
        "pokemonId": 807,
        "pokemonName": "Zeraora",
        "tier": "legendary",
        "delta": 5
    },
    {
        "id": "liliah-fettner",
        "name": "LILIAH FETTNER",
        "puzzles": 40,
        "plw": 120,
        "uscf": 712,
        "group": "King 17",
        "pokemonId": 640,
        "pokemonName": "Virizion",
        "tier": "legendary",
        "delta": 4
    },
    {
        "id": "adam-atwa",
        "name": "Adam Atwa",
        "puzzles": 39,
        "plw": 157,
        "uscf": 802,
        "group": "King 59",
        "pokemonId": 243,
        "pokemonName": "Raikou",
        "tier": "legendary",
        "delta": 1
    },
    {
        "id": "walter-gooch-raushenbush",
        "name": "Walter Gooch-Raushenbush",
        "puzzles": 39,
        "plw": 137,
        "uscf": 1256,
        "group": "Super King 3",
        "pokemonId": 1014,
        "pokemonName": "Okidogi",
        "tier": "legendary",
        "delta": 2
    },
    {
        "id": "rami-padukone-mitter",
        "name": "Rami Padukone-Mitter",
        "puzzles": 32,
        "plw": 96,
        "uscf": 1147,
        "group": "King 11",
        "pokemonId": 961,
        "pokemonName": "Wugtrio",
        "tier": "final",
        "delta": 1
    },
    {
        "id": "dylen-duke",
        "name": "Dylen Duke",
        "puzzles": 27,
        "plw": 164,
        "uscf": 376,
        "group": "Bishop 2",
        "pokemonId": 891,
        "pokemonName": "Kubfu",
        "tier": "legendary",
        "delta": 0
    },
    {
        "id": "elise-labarbera",
        "name": "Elise LaBarbera",
        "puzzles": 24,
        "plw": 48,
        "uscf": 0,
        "group": "Rook 2",
        "pokemonId": 408,
        "pokemonName": "Cranidos",
        "tier": "basic",
        "delta": 1
    },
    {
        "id": "arin-dhami",
        "name": "Arin Dhami",
        "puzzles": 24,
        "plw": 48,
        "uscf": 0,
        "group": "Rook 5",
        "pokemonId": 459,
        "pokemonName": "Snover",
        "tier": "basic",
        "delta": 5
    },
    {
        "id": "kai-tang",
        "name": "Kai Tang",
        "puzzles": 23,
        "plw": 56,
        "uscf": 0,
        "group": "King 7",
        "pokemonId": 561,
        "pokemonName": "Sigilyph",
        "tier": "evolved",
        "delta": 1
    },
    {
        "id": "elliot-koehler",
        "name": "Elliot Koehler",
        "puzzles": 23,
        "plw": 43,
        "uscf": 0,
        "group": "Pawn 5",
        "pokemonId": 621,
        "pokemonName": "Druddigon",
        "tier": "basic",
        "delta": 0
    },
    {
        "id": "nicephore-suter",
        "name": "Nicephore Suter",
        "puzzles": 20,
        "plw": 115,
        "uscf": 0,
        "group": "King 1",
        "pokemonId": 484,
        "pokemonName": "Palkia",
        "tier": "legendary",
        "delta": 1
    },
    {
        "id": "weston-hu",
        "name": "Weston Hu",
        "puzzles": 17,
        "plw": 56,
        "uscf": 431,
        "group": "King 16",
        "pokemonId": 947,
        "pokemonName": "Brambleghast",
        "tier": "evolved",
        "delta": 5
    },
    {
        "id": "alejandro-sheikh",
        "name": "Alejandro Sheikh",
        "puzzles": 14,
        "plw": 53,
        "uscf": 702,
        "group": "King 15",
        "pokemonId": 441,
        "pokemonName": "Chatot",
        "tier": "evolved",
        "delta": 3
    },
    {
        "id": "andrew-li",
        "name": "Andrew Li",
        "puzzles": 12,
        "plw": 36,
        "uscf": 1300,
        "group": "King 55",
        "pokemonId": 204,
        "pokemonName": "Pineco",
        "tier": "basic",
        "delta": 0
    },
    {
        "id": "sammy-fialkovskiy",
        "name": "Sammy Fialkovskiy",
        "puzzles": 11,
        "plw": 163,
        "uscf": 550,
        "group": "King 85",
        "pokemonId": 1016,
        "pokemonName": "Fezandipiti",
        "tier": "legendary",
        "delta": 3
    },
    {
        "id": "chase-grant",
        "name": "Chase grant",
        "puzzles": 10,
        "plw": 70,
        "uscf": 301,
        "group": "Queen 9",
        "pokemonId": 214,
        "pokemonName": "Heracross",
        "tier": "evolved",
        "delta": 4
    },
    {
        "id": "rishiv-doshi",
        "name": "Rishiv Doshi",
        "puzzles": 8,
        "plw": 26,
        "uscf": 0,
        "group": "Queen 4",
        "pokemonId": 539,
        "pokemonName": "Sawk",
        "tier": "basic",
        "delta": 2
    },
    {
        "id": "brian-silverman",
        "name": "Brian Silverman",
        "puzzles": 6,
        "plw": 28,
        "uscf": 1035,
        "group": "Super King 47",
        "pokemonId": 133,
        "pokemonName": "Eevee",
        "tier": "basic",
        "delta": 4
    },
    {
        "id": "wyatt-lawson",
        "name": "Wyatt Lawson",
        "puzzles": 5,
        "plw": 90,
        "uscf": 727,
        "group": "King 15",
        "pokemonId": 586,
        "pokemonName": "Sawsbuck",
        "tier": "final",
        "delta": 1
    },
    {
        "id": "dylan-wu",
        "name": "Dylan Wu",
        "puzzles": 5,
        "plw": 60,
        "uscf": 0,
        "group": "Rook 1",
        "pokemonId": 943,
        "pokemonName": "Mabosstiff",
        "tier": "evolved",
        "delta": 3
    },
    {
        "id": "yoomi-yoon-winawer",
        "name": "Yoomi Yoon-Winawer",
        "puzzles": 3,
        "plw": 21,
        "uscf": 241,
        "group": "Bishop 2",
        "pokemonId": 986,
        "pokemonName": "Brute Bonnet",
        "tier": "basic",
        "delta": 1
    },
    {
        "id": "glenn-gooch-raushenbush",
        "name": "Glenn Gooch-Raushenbush",
        "puzzles": 2,
        "plw": 96,
        "uscf": 1153,
        "group": "King 18",
        "pokemonId": 332,
        "pokemonName": "Cacturne",
        "tier": "final",
        "delta": 1
    },
    {
        "id": "sara-pui",
        "name": "Sara Pui",
        "puzzles": 2,
        "plw": 24,
        "uscf": 0,
        "group": "Pawn 2",
        "pokemonId": 556,
        "pokemonName": "Maractus",
        "tier": "basic",
        "delta": 4
    },
    {
        "id": "dylan-yip",
        "name": "Dylan Yip",
        "puzzles": 1,
        "plw": 32,
        "uscf": 0,
        "group": "King 4",
        "pokemonId": 846,
        "pokemonName": "Arrokuda",
        "tier": "basic",
        "delta": 5
    },
    {
        "id": "jules-jaindl",
        "name": "Jules Jaindl",
        "puzzles": 1,
        "plw": 47,
        "uscf": 0,
        "group": "King 7",
        "pokemonId": 559,
        "pokemonName": "Scraggy",
        "tier": "basic",
        "delta": 5
    },
    {
        "id": "jacob-saleh",
        "name": "Jacob Saleh",
        "puzzles": 0,
        "plw": 20,
        "uscf": 320,
        "group": "King 1",
        "pokemonId": 607,
        "pokemonName": "Litwick",
        "tier": "basic",
        "delta": 0
    }
]