[
    {
        "id": "anastassi-xenos",
        "name": "Anastassi Xenos",
        "puzzles": 217,
        "plw": 661,
        "uscf": 793,
        "group": "King 27",
        "pokemonId": 891,
        "pokemonName": "Kubfu",
        "tier": "legendary",
        "delta": 4
    },
    {
        "id": "wyatt-lawson",
        "name": "Wyatt Lawson",
        "puzzles": 96,
        "plw": 298,
        "uscf": 1055,
        "group": "King 22",
        "pokemonId": 641,
        "pokemonName": "Tornadus",
        "tier": "legendary",
        "delta": 4
    },
    {
        "id": "liliah-fettner",
        "name": "LILIAH FETTNER",
        "puzzles": 91,
        "plw": 283,
        "uscf": 701,
        "group": "King 19",
        "pokemonId": 800,
        "pokemonName": "Necrozma",
        "tier": "legendary",
        "delta": 4
    },
    {
        "id": "chase-grant",
        "name": "Chase grant",
        "puzzles": 44,
        "plw": 88,
        "uscf": 546,
        "group": "King 1",
        "pokemonId": 448,
        "pokemonName": "Lucario",
        "tier": "final",
        "delta": 0
    },
    {
        "id": "isha-varma",
        "name": "Isha Varma",
        "puzzles": 31,
        "plw": 93,
        "uscf": 1291,
        "group": "King 22",
        "pokemonId": 53,
        "pokemonName": "Persian",
        "tier": "final",
        "delta": 2
    },
    {
        "id": "adam-atwa",
        "name": "Adam Atwa",
        "puzzles": 21,
        "plw": 73,
        "uscf": 854,
        "group": "King 70",
        "pokemonId": 569,
        "pokemonName": "Garbodor",
        "tier": "evolved",
        "delta": 4
    },
    {
        "id": "dylan-yip",
        "name": "Dylan Yip",
        "puzzles": 20,
        "plw": 40,
        "uscf": 285,
        "group": "King 6",
        "pokemonId": 704,
        "pokemonName": "Goomy",
        "tier": "basic",
        "delta": 4
    },
    {
        "id": "parker-downing",
        "name": "PARKER DOWNING",
        "puzzles": 13,
        "plw": 36,
        "uscf": 204,
        "group": "King 34",
        "pokemonId": 263,
        "pokemonName": "Zigzagoon",
        "tier": "basic",
        "delta": 1
    },
    {
        "id": "theodore-meng",
        "name": "Theodore Meng",
        "puzzles": 11,
        "plw": 63,
        "uscf": 1340,
        "group": "Super King 37",
        "pokemonId": 956,
        "pokemonName": "Espathra",
        "tier": "evolved",
        "delta": 3
    },
    {
        "id": "drew-murphy",
        "name": "Drew Murphy",
        "puzzles": 7,
        "plw": 21,
        "uscf": 1090,
        "group": "King 23",
        "pokemonId": 417,
        "pokemonName": "Pachirisu",
        "tier": "basic",
        "delta": 1
    },
    {
        "id": "chloe-yip",
        "name": "Chloe Yip",
        "puzzles": 6,
        "plw": 28,
        "uscf": 1205,
        "group": "King 17",
        "pokemonId": 302,
        "pokemonName": "Sableye",
        "tier": "basic",
        "delta": 4
    }
]